ssmp/__init__.py
ssmp/aws.py
ssmp/main.py
ssmp-0.0.7.data/scripts/main.py
ssmp-0.0.7.dist-info/LICENSE
ssmp-0.0.7.dist-info/METADATA
ssmp-0.0.7.dist-info/WHEEL
ssmp-0.0.7.dist-info/entry_points.txt
ssmp-0.0.7.dist-info/top_level.txt
ssmp-0.0.7.dist-info/RECORD
