Metadata-Version: 2.1
Name: ssmp
Version: 0.0.7
Summary: CLI tool for AWS SSM parameter
Home-page: https://github.com/yikaus/ssmp
Author: Kevin Yi
Author-email: yikaus@gmail.com
License: MIT License
Requires-Dist: boto3
Requires-Dist: click
Requires-Dist: pandas
